bioduck/__init__.py
bioduck/main.py
bioduck/sql/__init__.py
bioduck/sql/ncbi/__init__.py
bioduck/sql/ncbi/enums.sql
bioduck/sql/ncbi/init.sql
bioduck/sql/ncbi/load_assembly_genbank.sql
bioduck/sql/ncbi/load_assembly_refseq.sql
bioduck/sql/ncbi/load_taxonomy.sql
bioduck-0.1.0.dist-info/METADATA
bioduck-0.1.0.dist-info/WHEEL
bioduck-0.1.0.dist-info/entry_points.txt
bioduck-0.1.0.dist-info/top_level.txt
bioduck-0.1.0.dist-info/RECORD
