Metadata-Version: 2.2
Name: bioduck
Version: 0.1.0
Summary: A CLI tool for running SQL files against DuckDB and exploring data interactively
Requires-Python: >=3.11
Requires-Dist: click>=8.1.8
Requires-Dist: duckdb>=1.2.1
Requires-Dist: requests>=2.28.0
